smugcli/__init__.py
smugcli/__main__.py
smugcli/persistent_dict.py
smugcli/smugcli.py
smugcli/smugcli_commands.py
smugcli/smugmug.py
smugcli/smugmug_fs.py
smugcli/smugmug_oauth.py
smugcli/smugmug_shell.py
smugcli/stdout_interceptor.py
smugcli/task_manager.py
smugcli/terminal_size.py
smugcli/thread_pool.py
smugcli/thread_safe_print.py
smugcli/version.py
smugcli-1.0.8.dist-info/LICENSE
smugcli-1.0.8.dist-info/METADATA
smugcli-1.0.8.dist-info/WHEEL
smugcli-1.0.8.dist-info/entry_points.txt
smugcli-1.0.8.dist-info/top_level.txt
smugcli-1.0.8.dist-info/RECORD
