Metadata-Version: 2.2
Name: smugcli
Version: 1.0.8
Summary: Command line tool for SmugMug
Home-page: https://github.com/graveljp/smugcli
Author: Jean-Philippe Gravel
Author-email: jpgravel@gmail.com
Classifier: License :: OSI Approved :: MIT License
Classifier: Operating System :: OS Independent
Classifier: Programming Language :: Python
Classifier: Programming Language :: Python :: 3
Classifier: Programming Language :: Python :: 3.8
Classifier: Programming Language :: Python :: 3.9
Classifier: Programming Language :: Python :: 3.10
Classifier: Programming Language :: Python :: 3.11
Classifier: Programming Language :: Python :: 3.12
Classifier: Programming Language :: Python :: 3.13
License-File: LICENSE
Requires-Dist: bottle>=0.12.13
Requires-Dist: rauth>=0.7.3
Requires-Dist: requests>=2.13.0
Requires-Dist: requests-oauthlib>=0.7.0
Requires-Dist: colorama>=0.3.9; platform_system == "Windows"
Requires-Dist: hachoir>=3.0
Requires-Dist: jsonpath-ng>=1.5.3
Dynamic: author
Dynamic: author-email
Dynamic: classifier
Dynamic: description
Dynamic: description-content-type
Dynamic: home-page
Dynamic: requires-dist
Dynamic: summary
